extractor/__init__.py
extractor/core.py
letter_extractor-0.1.1.dist-info/licenses/LICENSE
letter_extractor-0.1.1.dist-info/METADATA
letter_extractor-0.1.1.dist-info/WHEEL
letter_extractor-0.1.1.dist-info/top_level.txt
letter_extractor-0.1.1.dist-info/RECORD
