Metadata-Version: 2.4
Name: letter_extractor
Version: 0.1.1
Summary: Library to extract only letters from text using Unicode-safe regular expressions
Author: Olha Yukhnenko
License: MIT
Classifier: Programming Language :: Python :: 3
Classifier: Operating System :: OS Independent
Requires-Python: >=3.8
License-File: LICENSE
Provides-Extra: dev
Requires-Dist: build; extra == "dev"
Requires-Dist: pytest>=8.0; extra == "dev"
Requires-Dist: twine; extra == "dev"
Provides-Extra: keywords
Requires-Dist: text; extra == "keywords"
Requires-Dist: letters; extra == "keywords"
Requires-Dist: regex; extra == "keywords"
Requires-Dist: unicode; extra == "keywords"
Requires-Dist: extractor; extra == "keywords"
Requires-Dist: NLP; extra == "keywords"
Dynamic: license-file
